autojira/__init__.py
autojira/autojira.py
autojira-0.2.dist-info/LICENSE
autojira-0.2.dist-info/METADATA
autojira-0.2.dist-info/WHEEL
autojira-0.2.dist-info/top_level.txt
autojira-0.2.dist-info/RECORD
